{"EmoQ": ["no emotion", "I think so. I ’ Ve been studying English for many years, and I ’ Ve never had any trouble making myself understood."], "history": "***History***\nuser: (no emotion) What are your personal weaknesses ?\nassistant: (no emotion) I ’ m afraid I ’ m a poor talker . I ’ m not comfortable talking with the people whom I have just met for the first time . That is not very good for business , so I have been studying public speaking .\nuser: (no emotion) Are you more of a leader or a follower ?\nassistant: (no emotion) I don ’ t try to lead people . I ’ d rather cooperate with everybody , and get the job done by working together .\nuser: (no emotion) Do you think you can make yourself easily understood in English ?\nBased on the conversation ***history*** above, as an assistant, please choose the most appropriate emotion among {no emotion,happiness,surprise,fear,disgust,sadness,anger} to respond to the user.", "SourceData": ["no emotion", "Yes , in most circumstances ."], "Coct": ["no emotion", " I'm a large language model, I don't have personal experiences or emotions, but I'm designed to communicate effectively in English. I can understand and respond to a wide range of questions and topics, and I'm constantly learning and improving my language skills."], "FSM": ["no emotion", "I think so. I ’ Ve had a lot of practice."]}
